bias_mutant/Coreference.py
bias_mutant/Entity.py
bias_mutant/MutantGeneration.py
bias_mutant/Phrase.py
bias_mutant/Position.py
bias_mutant/__init__.py
bias_mutant/utils.py
bias_rv/BiasRV.py
bias_rv/Coreference.py
bias_rv/Entity.py
bias_rv/MutantGeneration.py
bias_rv/Phrase.py
bias_rv/Position.py
bias_rv/__init__.py
bias_rv/utils.py
bias_rv/asset/gender_associated_word/masculine-feminine-cleaned.txt
bias_rv/asset/gender_associated_word/masculine-feminine-person.txt
bias_rv/asset/gender_associated_word/masculine-feminine.txt
bias_rv/asset/gender_computer/female_names_only.csv
bias_rv/asset/gender_computer/male_names_only.csv
bias_rv/asset/gender_computer/unique_female_names_and_country.csv
bias_rv/asset/gender_computer/unique_male_names_and_country.csv
bias_rv/asset/gender_computer/unique_name_country.csv
bias_rv-0.0.9.dist-info/METADATA
bias_rv-0.0.9.dist-info/WHEEL
bias_rv-0.0.9.dist-info/top_level.txt
bias_rv-0.0.9.dist-info/RECORD
