Metadata-Version: 2.1
Name: bias-rv
Version: 0.0.9
Summary: A package to generate biased mutants for texts
Home-page: https://github.com/soarsmu/BiasFinder
Author: Zhou Yang
Author-email: zyang@smu.edu.sg
License: UNKNOWN
Platform: UNKNOWN
Classifier: Programming Language :: Python :: 3
Classifier: License :: OSI Approved :: MIT License
Classifier: Operating System :: OS Independent
